BenbanfaXueGit/README.md
BenbanfaXueGit/__init__.py
BenbanfaXueGit/__main__.py
BenbanfaXueGit/file.epub
BenbanfaXueGit/index.html
BenbanfaXueGit/css/__init__.py
BenbanfaXueGit/css/annotations.css
BenbanfaXueGit/css/main.css
BenbanfaXueGit/css/normalize.css
BenbanfaXueGit/css/popup.css
BenbanfaXueGit/font/__init__.py
BenbanfaXueGit/font/fontello.eot
BenbanfaXueGit/font/fontello.svg
BenbanfaXueGit/font/fontello.ttf
BenbanfaXueGit/font/fontello.woff
BenbanfaXueGit/img/__init__.py
BenbanfaXueGit/img/annotator-glyph-sprite.png
BenbanfaXueGit/img/annotator-icon-sprite.png
BenbanfaXueGit/img/apple-touch-icon.png
BenbanfaXueGit/img/cancelfullscreen.png
BenbanfaXueGit/img/close.png
BenbanfaXueGit/img/fullscreen.png
BenbanfaXueGit/img/loader.gif
BenbanfaXueGit/img/menu-icon.png
BenbanfaXueGit/img/save.png
BenbanfaXueGit/img/saved.png
BenbanfaXueGit/img/settings-s.png
BenbanfaXueGit/img/settings.png
BenbanfaXueGit/img/star.png
BenbanfaXueGit/js/__init__.py
BenbanfaXueGit/js/epub.js
BenbanfaXueGit/js/epub.min.js
BenbanfaXueGit/js/epub.min.map
BenbanfaXueGit/js/hooks.min.js
BenbanfaXueGit/js/hooks.min.map
BenbanfaXueGit/js/reader.js
BenbanfaXueGit/js/reader.js.map
BenbanfaXueGit/js/reader.min.js
BenbanfaXueGit/js/reader.min.map
BenbanfaXueGit/js/hooks/__init__.py
BenbanfaXueGit/js/hooks/extensions/__init__.py
BenbanfaXueGit/js/hooks/extensions/highlight.js
BenbanfaXueGit/js/libs/__init__.py
BenbanfaXueGit/js/libs/jquery.min.js
BenbanfaXueGit/js/libs/localforage.min.js
BenbanfaXueGit/js/libs/screenfull.js
BenbanfaXueGit/js/libs/screenfull.min.js
BenbanfaXueGit/js/libs/zip.min.js
BenbanfaXueGit/js/plugins/__init__.py
BenbanfaXueGit/js/plugins/hypothesis.js
BenbanfaXueGit/js/plugins/search.js
benbanfa_xue_git-2024.3.4.0.dist-info/METADATA
benbanfa_xue_git-2024.3.4.0.dist-info/WHEEL
benbanfa_xue_git-2024.3.4.0.dist-info/entry_points.txt
benbanfa_xue_git-2024.3.4.0.dist-info/top_level.txt
benbanfa_xue_git-2024.3.4.0.dist-info/RECORD
